MANIFEST.in
README.rst
setup.py
sjc_funniest/__init__.py
sjc_funniest/command_line.py
sjc_funniest/text.py
sjc_funniest.egg-info/PKG-INFO
sjc_funniest.egg-info/SOURCES.txt
sjc_funniest.egg-info/dependency_links.txt
sjc_funniest.egg-info/entry_points.txt
sjc_funniest.egg-info/not-zip-safe
sjc_funniest.egg-info/requires.txt
sjc_funniest.egg-info/top_level.txt